CHANGELOG.md
LICENSE.txt
culqi/__init__.py
culqi/client.py
culqi/resources/__init__.py
culqi/resources/base.py
culqi/resources/card.py
culqi/resources/charge.py
culqi/resources/customer.py
culqi/resources/event.py
culqi/resources/iin.py
culqi/resources/order.py
culqi/resources/plan.py
culqi/resources/refund.py
culqi/resources/subscription.py
culqi/resources/token.py
culqi/resources/transfer.py
culqi/schemas/__init__.py
culqi/schemas/card.py
culqi/schemas/charge.py
culqi/schemas/customer.py
culqi/schemas/order.py
culqi/schemas/plan.py
culqi/schemas/refund.py
culqi/schemas/subscription.py
culqi/utils/__init__.py
culqi/utils/errors.py
culqi/utils/status_codes.py
culqi/utils/urls.py
culqi/version.py
culqi_api_python-2.0.0.dist-info/LICENSE.txt
culqi_api_python-2.0.0.dist-info/WHEEL
culqi_api_python-2.0.0.dist-info/METADATA
culqi_api_python-2.0.0.dist-info/RECORD
