Metadata-Version: 2.1
Name: culqi-api-python
Version: 2.0.0
Summary: Biblioteca de Culqi en Python
Home-page: https://github.com/softbutterfly/culqi-api-python
License: MIT
Keywords: Softbutterfly,Culqi,Culqi API
Author: SoftButterfly Development Team
Author-email: dev@softbutterfly.io
Requires-Python: >=3.7,<4.0.0
Classifier: Development Status :: 5 - Production/Stable
Classifier: Intended Audience :: Developers
Classifier: License :: OSI Approved :: MIT License
Classifier: Natural Language :: English
Classifier: Programming Language :: Python :: 3
Classifier: Programming Language :: Python :: 3.10
Classifier: Programming Language :: Python :: 3.6
Classifier: Programming Language :: Python :: 3.7
Classifier: Programming Language :: Python :: 3.8
Classifier: Programming Language :: Python :: 3.9
Classifier: Topic :: Software Development :: Libraries :: Python Modules
Requires-Dist: jsonschema (>=4.4.0,<5.0.0)
Requires-Dist: requests (>=2.27.1,<3.0.0)
Project-URL: Bug Tracker, https://github.com/softbutterfly/culqi-api-python/issues
Project-URL: Documentation, https://github.com/softbutterfly/culqi-api-python/wiki
Project-URL: Download, https://github.com/softbutterfly/culqi-api-python/archive/2.0.0.tar.gz
Project-URL: Repository, https://github.com/softbutterfly/culqi-api-python
